codetrack/__init__.py
codetrack/codetrack.py
codetrack-1.0.4.dist-info/METADATA
codetrack-1.0.4.dist-info/WHEEL
codetrack-1.0.4.dist-info/top_level.txt
codetrack-1.0.4.dist-info/RECORD
