Metadata-Version: 2.1
Name: codetrack
Version: 1.0.4
Summary: Calculate your carbon emission !
Home-page: https://github.com/loner2424
Author: Sahil Sobhani
Author-email: sahilsobhai4@gmail.com
Project-URL: Bug Tracker, https://github.com/loner2424
Project-URL: repository, https://github.com/loner2424
Classifier: Programming Language :: Python :: 3
Classifier: License :: OSI Approved :: MIT License
Classifier: Operating System :: OS Independent
Requires-Python: >=3.6
Requires-Dist: psutil
Requires-Dist: pynvml
Requires-Dist: py-cpuinfo
